random_word/__init__.py
random_word/config.yml.gpg
random_word/database/words.json
random_word/random_word.py
random_word/services/__init__.py
random_word/services/apininjas.py
random_word/services/local.py
random_word/services/wordnik.py
random_word/tests/__init__.py
random_word/tests/test_apininjas.py
random_word/tests/test_random_word.py
random_word/tests/test_wordnik.py
random_word/utils/__init__.py
random_word/utils/retry_generator.py
random_word/utils/utils.py
random_word-1.0.12.dist-info/LICENSE
random_word-1.0.12.dist-info/METADATA
random_word-1.0.12.dist-info/WHEEL
random_word-1.0.12.dist-info/RECORD
